{
  "title": "Kelvin Mo",
  "tagline": "Biologist, data scientist, and innovator at the intersection of cancer immunology and computation.",
  "description": "Kelvin Mo is a Harvard BBS PhD student building translational cancer immunology programs powered by computation.",
  "url": "https://kelvin-mo.com",
  "author": {
    "name": "Kelvin Mo",
    "email": "kelvin.mo@hotmail.com",
    "linkedin": "https://www.linkedin.com/in/kelvin-mo/",
    "github": "https://github.com/kelvinmo0513",
    "scholar": "#",
    "location": "Cambridge, MA",
    "headshot": "/assets/kelvinmo-profile.png"
  },
  "seo": {
    "keywords": "Kelvin Mo, Harvard, Biological and Biomedical Sciences, cancer immunology, computational biology, spatial transcriptomics, CAR T",
    "image": "/assets/og-cover.jpg",
    "twitter": "@kelvinmo"
  },
  "nav": [
    { "title": "About", "url": "/about/" },
    { "title": "Projects", "url": "/projects/" },
    { "title": "Publications", "url": "/publications/" },
    { "title": "CV", "url": "/cv/" },
    { "title": "Contact", "url": "/contact/" }
  ]
}
